riberry/__init__.py
riberry/app/__init__.py
riberry/app/actions/__init__.py
riberry/app/actions/artifacts.py
riberry/app/actions/executions.py
riberry/app/actions/external_task.py
riberry/app/actions/jobs.py
riberry/app/actions/notify.py
riberry/app/actions/reports.py
riberry/app/actions/shared_data.py
riberry/app/addons/__init__.py
riberry/app/addons/base.py
riberry/app/backends/__init__.py
riberry/app/backends/base.py
riberry/app/backends/impl/__init__.py
riberry/app/backends/impl/celery/__init__.py
riberry/app/backends/impl/celery/addons/__init__.py
riberry/app/backends/impl/celery/addons/background.py
riberry/app/backends/impl/celery/addons/base.py
riberry/app/backends/impl/celery/addons/capacity/__init__.py
riberry/app/backends/impl/celery/addons/capacity/priority_queue.py
riberry/app/backends/impl/celery/addons/external_task_receiver.py
riberry/app/backends/impl/celery/addons/scale.py
riberry/app/backends/impl/celery/base.py
riberry/app/backends/impl/celery/executor.py
riberry/app/backends/impl/celery/extension.py
riberry/app/backends/impl/celery/patch.py
riberry/app/backends/impl/celery/signals.py
riberry/app/backends/impl/celery/tasks.py
riberry/app/backends/impl/celery/tracker.py
riberry/app/backends/impl/pool/__init__.py
riberry/app/backends/impl/pool/base.py
riberry/app/backends/impl/pool/exc.py
riberry/app/backends/impl/pool/log.py
riberry/app/backends/impl/pool/task_queue/__init__.py
riberry/app/backends/impl/pool/task_queue/base.py
riberry/app/backends/impl/pool/tasks/__init__.py
riberry/app/backends/impl/pool/tasks/background.py
riberry/app/backends/impl/pool/tasks/executor.py
riberry/app/backends/impl/pool/tasks/external_task_receiver.py
riberry/app/backends/impl/pool/tracker.py
riberry/app/backends/tracker.py
riberry/app/base.py
riberry/app/context/__init__.py
riberry/app/context/artifact.py
riberry/app/context/current.py
riberry/app/context/event_registry.py
riberry/app/context/external_task.py
riberry/app/context/flow.py
riberry-0.10.22.dist-info/entry_points.txt
riberry-0.10.22.dist-info/LICENSE
riberry-0.10.22.dist-info/WHEEL
riberry-0.10.22.dist-info/METADATA
riberry-0.10.22.dist-info/RECORD
